README.md
setup.cfg
setup.py
paqueteseleccioninstancias/__init__.py
paqueteseleccioninstancias/datos_equilibrados.py
paqueteseleccioninstancias/datos_no_equilibrados.py
paqueteseleccioninstancias/pruebas_uso_equilibrados.py
paqueteseleccioninstancias/pruebas_uso_no_equilibrados.py
paqueteseleccioninstancias/iselection/__init__.py
paqueteseleccioninstancias/iselection/mathadvancedfuncs.py
paqueteseleccioninstancias/iselection/mymathsutils.py
seleccioninstancias.egg-info/PKG-INFO
seleccioninstancias.egg-info/SOURCES.txt
seleccioninstancias.egg-info/dependency_links.txt
seleccioninstancias.egg-info/requires.txt
seleccioninstancias.egg-info/top_level.txt