Metadata-Version: 1.0
Name: seleccioninstancias
Version: 0.5
Summary: Paquete con funciones que permiten realizar seleccion de instancias
Home-page: https://github.com/VicBoxMS/SeleccionInstancias
Author: Victor Martinez Santiago @vicbox
Author-email: UNKNOWN
License: MIT
Platform: UNKNOWN
